django_ai_agent/__init__.py
django_ai_agent/apps.py
django_ai_agent/enums.py
django_ai_agent/exceptions.py
django_ai_agent/types.py
django_ai_agent/admin/__init__.py
django_ai_agent/admin/agent.py
django_ai_agent/admin/conversation.py
django_ai_agent/admin/guardrail.py
django_ai_agent/admin/message.py
django_ai_agent/admin/model_provider.py
django_ai_agent/admin/model_settings.py
django_ai_agent/admin/prompt.py
django_ai_agent/admin/tool.py
django_ai_agent/admin/transcription_model.py
django_ai_agent/admin/document/__init__.py
django_ai_agent/admin/document/document.py
django_ai_agent/admin/document/document_chunk.py
django_ai_agent/admin/embedding/__init__.py
django_ai_agent/admin/embedding/openai.py
django_ai_agent/admin/embedding/voyageai.py
django_ai_agent/admin/mixins/__init__.py
django_ai_agent/admin/mixins/soft_validation.py
django_ai_agent/entities/__init__.py
django_ai_agent/entities/document.py
django_ai_agent/entities/guardrail.py
django_ai_agent/management/__init__.py
django_ai_agent/management/commands/__init__.py
django_ai_agent/management/commands/sync_tools.py
django_ai_agent/migrations/0001_initial.py
django_ai_agent/migrations/0002_tool_max_retries_tool_strict.py
django_ai_agent/migrations/0003_create_history.py
django_ai_agent/migrations/0004_transcription_model.py
django_ai_agent/migrations/0005_add_circuit_breaker_fields.py
django_ai_agent/migrations/0006_alter_historicaltool_max_calls_and_more.py
django_ai_agent/migrations/__init__.py
django_ai_agent/models/__init__.py
django_ai_agent/models/agent.py
django_ai_agent/models/conversation.py
django_ai_agent/models/guardrail.py
django_ai_agent/models/message.py
django_ai_agent/models/model_provider.py
django_ai_agent/models/model_settings.py
django_ai_agent/models/prompt.py
django_ai_agent/models/tool.py
django_ai_agent/models/transcription_model.py
django_ai_agent/models/abstract/__init__.py
django_ai_agent/models/abstract/timestamp.py
django_ai_agent/models/document/__init__.py
django_ai_agent-0.0.13.dist-info/METADATA
django_ai_agent-0.0.13.dist-info/WHEEL
django_ai_agent-0.0.13.dist-info/RECORD
